{
    "format_version": "1.12",
    "minecraft:recipe_shaped": {
      "description": {
        "identifier": "backpack:backpack_copperas"
      },
      "tags": [
        "crafting_table"
      ],
      "pattern": [
        " C ",
        "CBC",
        " C "
      ],
      "key": {
        "C": {
          "item": "minecraft:copper_ingot"
        },
        "B": {
          "item": "backpack:backpack"
        }
      },
      "result": {
        "item": "backpack:backpack_copper"
      }
    }
  }
  